{
  "main": {
    "id": "532a95fd725b4a12",
    "type": "split",
    "children": [
      {
        "id": "99f4c8aea078e056",
        "type": "tabs",
        "children": [
          {
            "id": "605dc2c2799838d1",
            "type": "leaf",
            "state": {
              "type": "markdown",
              "state": {
                "file": "_posts/诗歌语言的陌生化.md",
                "mode": "source",
                "source": false
              }
            }
          }
        ]
      }
    ],
    "direction": "vertical"
  },
  "left": {
    "id": "49cf8bd766cc1ee9",
    "type": "split",
    "children": [
      {
        "id": "e84fc60b39596961",
        "type": "tabs",
        "children": [
          {
            "id": "b62af949bb640cb0",
            "type": "leaf",
            "state": {
              "type": "file-explorer",
              "state": {
                "sortOrder": "alphabetical"
              }
            }
          },
          {
            "id": "8b5e36c0f5426fc3",
            "type": "leaf",
            "state": {
              "type": "search",
              "state": {
                "query": "",
                "matchingCase": false,
                "explainSearch": false,
                "collapseAll": false,
                "extraContext": false,
                "sortOrder": "alphabetical"
              }
            }
          },
          {
            "id": "d4ef0972c1debea9",
            "type": "leaf",
            "state": {
              "type": "starred",
              "state": {}
            }
          }
        ]
      }
    ],
    "direction": "horizontal",
    "width": 300
  },
  "right": {
    "id": "b6161a6a4e8aaaf6",
    "type": "split",
    "children": [
      {
        "id": "7cbfaf88f5e576c7",
        "type": "tabs",
        "children": [
          {
            "id": "4e5a5263e61e98b1",
            "type": "leaf",
            "state": {
              "type": "backlink",
              "state": {
                "file": "_posts/诗歌语言的陌生化.md",
                "collapseAll": false,
                "extraContext": false,
                "sortOrder": "alphabetical",
                "showSearch": false,
                "searchQuery": "",
                "backlinkCollapsed": false,
                "unlinkedCollapsed": true
              }
            }
          },
          {
            "id": "ed1c7e57d2138584",
            "type": "leaf",
            "state": {
              "type": "outgoing-link",
              "state": {
                "file": "_posts/诗歌语言的陌生化.md",
                "linksCollapsed": false,
                "unlinkedCollapsed": true
              }
            }
          },
          {
            "id": "1a0d9922247d0281",
            "type": "leaf",
            "state": {
              "type": "tag",
              "state": {
                "sortOrder": "frequency",
                "useHierarchy": true
              }
            }
          },
          {
            "id": "2b5001a0ccf35dd8",
            "type": "leaf",
            "state": {
              "type": "outline",
              "state": {
                "file": "_posts/诗歌语言的陌生化.md"
              }
            }
          }
        ]
      }
    ],
    "direction": "horizontal",
    "width": 300,
    "collapsed": true
  },
  "ribbon": {
    "mostRecentAction": ""
  },
  "active": "605dc2c2799838d1",
  "lastOpenFiles": [
    "_posts/种类并查集.md",
    "_posts/诗歌语言的陌生化.md",
    "未命名.md"
  ]
}